simple_mcp_client/__init__.py
simple_mcp_client/config.py
simple_mcp_client/main.py
simple_mcp_client/config/default_config.json
simple_mcp_client/console/__init__.py
simple_mcp_client/console/chat_utils.py
simple_mcp_client/console/interface.py
simple_mcp_client/console/tool_formatter.py
simple_mcp_client/llm/__init__.py
simple_mcp_client/llm/base.py
simple_mcp_client/llm/deepseek.py
simple_mcp_client/llm/litellm.py
simple_mcp_client/llm/ollama.py
simple_mcp_client/llm/openai.py
simple_mcp_client/llm/openrouter.py
simple_mcp_client/llm/react_agent.py
simple_mcp_client/mcp/__init__.py
simple_mcp_client/mcp/connection.py
simple_mcp_client/mcp/exceptions.py
simple_mcp_client/mcp/langchain_adapter.py
simple_mcp_client/mcp/manager.py
simple_mcp_client/mcp/models.py
simple_mcp_client/mcp/server.py
simple_mcp_client/prompt/__init__.py
simple_mcp_client/prompt/system.py
simple_mcp_client-1.0.11.dist-info/licenses/LICENSE
tests/conftest.py
tests/test_chat_utils.py
tests/test_config.py
tests/test_config_script.py
tests/test_connection.py
tests/test_integration.py
tests/test_langchain_adapter.py
tests/test_react_agent.py
tests/test_react_chat.py
tests/test_server.py
tests/test_server_manager.py
simple_mcp_client-1.0.11.dist-info/METADATA
simple_mcp_client-1.0.11.dist-info/WHEEL
simple_mcp_client-1.0.11.dist-info/entry_points.txt
simple_mcp_client-1.0.11.dist-info/top_level.txt
simple_mcp_client-1.0.11.dist-info/RECORD
