Metadata-Version: 2.4
Name: simple-mcp-client
Version: 1.0.11
Summary: A simple MCP client for testing MCP servers
Author-email: Lewis Guo <guolisen@gmail.com>
License: MIT
Project-URL: Homepage, https://github.com/guolisen/simple-mcp-client
Project-URL: Bug Tracker, https://github.com/guolisen/simple-mcp-client/issues
Classifier: Development Status :: 3 - Alpha
Classifier: Intended Audience :: Developers
Classifier: License :: OSI Approved :: MIT License
Classifier: Programming Language :: Python :: 3
Classifier: Programming Language :: Python :: 3.10
Classifier: Programming Language :: Python :: 3.11
Requires-Python: >=3.10
License-File: LICENSE
Requires-Dist: mcp>=1.0.0
Requires-Dist: httpx>=0.20.0
Requires-Dist: prompt-toolkit>=3.0.0
Requires-Dist: click>=8.0.0
Requires-Dist: rich>=10.0.0
Requires-Dist: python-dotenv>=0.19.0
Requires-Dist: setuptools>=78.1.0
Requires-Dist: wheel>=0.45.1
Requires-Dist: twine>=6.1.0
Requires-Dist: pkginfo>=1.12.1.2
Requires-Dist: urllib3>=2.3.0
Requires-Dist: requests-toolbelt>=1.0.0
Requires-Dist: build>=1.2.2.post1
Requires-Dist: langchain-mcp-adapters>=0.1.9
Requires-Dist: langgraph>=0.5.4
Requires-Dist: langchain>=0.3.27
Requires-Dist: langchain-openai>=0.3.28
Requires-Dist: psutil>=7.0.0
Requires-Dist: pytest>=8.4.1
Requires-Dist: pytest-asyncio>=1.1.0
Requires-Dist: pytest-cov>=6.2.1
Dynamic: license-file
